snapshot_pyppeteer/__init__.py
snapshot_pyppeteer/_version.py
snapshot_pyppeteer/snapshot.py
snapshot_pyppeteer-0.0.1.dist-info/LICENSE
snapshot_pyppeteer-0.0.1.dist-info/METADATA
snapshot_pyppeteer-0.0.1.dist-info/WHEEL
snapshot_pyppeteer-0.0.1.dist-info/top_level.txt
snapshot_pyppeteer-0.0.1.dist-info/RECORD
